carpo_student/__init__.py
carpo_student/_version.py
carpo_student/handlers.py
carpo_student/__pycache__/__init__.cpython-310.pyc
carpo_student/__pycache__/_version.cpython-310.pyc
carpo_student/__pycache__/handlers.cpython-310.pyc
carpo_student/labextension/build_log.json
carpo_student/labextension/package.json
carpo_student/labextension/schemas/carpo-student/package.json.orig
carpo_student/labextension/schemas/carpo-student/plugin.json
carpo_student/labextension/static/lib_index_js.1ab82cd135d2773bd89f.js
carpo_student/labextension/static/lib_index_js.1ab82cd135d2773bd89f.js.map
carpo_student/labextension/static/lib_index_js.2815a4b56dd754da07fc.js
carpo_student/labextension/static/lib_index_js.2815a4b56dd754da07fc.js.map
carpo_student/labextension/static/lib_index_js.39449b54e3c621ab5ab1.js
carpo_student/labextension/static/lib_index_js.39449b54e3c621ab5ab1.js.map
carpo_student/labextension/static/lib_index_js.578305d228ac41b40508.js
carpo_student/labextension/static/lib_index_js.578305d228ac41b40508.js.map
carpo_student/labextension/static/lib_index_js.645f26d5c0758a65bf9e.js
carpo_student/labextension/static/lib_index_js.645f26d5c0758a65bf9e.js.map
carpo_student/labextension/static/lib_index_js.6d65867b0abc2ecb4b56.js
carpo_student/labextension/static/lib_index_js.6d65867b0abc2ecb4b56.js.map
carpo_student/labextension/static/lib_index_js.702cd083cba688e6ae07.js
carpo_student/labextension/static/lib_index_js.702cd083cba688e6ae07.js.map
carpo_student/labextension/static/lib_index_js.7e4008f8fabff4ded8cf.js
carpo_student/labextension/static/lib_index_js.7e4008f8fabff4ded8cf.js.map
carpo_student/labextension/static/lib_index_js.862b6565e7aa60684074.js
carpo_student/labextension/static/lib_index_js.862b6565e7aa60684074.js.map
carpo_student/labextension/static/lib_index_js.9124f3f9c33847d2d64a.js
carpo_student/labextension/static/lib_index_js.9124f3f9c33847d2d64a.js.map
carpo_student/labextension/static/lib_index_js.bff90a9e25f5c048ceb3.js
carpo_student-0.2.9.dist-info/LICENSE
carpo_student-0.2.9.dist-info/METADATA
carpo_student-0.2.9.dist-info/WHEEL
carpo_student-0.2.9.dist-info/top_level.txt
carpo_student-0.2.9.dist-info/RECORD
